aws_cdk_update_checker/__init__.py
aws_cdk_update_checker/main.py
aws_cdk_update_checker-0.0.14.dist-info/entry_points.txt
aws_cdk_update_checker-0.0.14.dist-info/LICENSE
aws_cdk_update_checker-0.0.14.dist-info/WHEEL
aws_cdk_update_checker-0.0.14.dist-info/METADATA
aws_cdk_update_checker-0.0.14.dist-info/RECORD
